[{"_id":"58784766786d2c0d72ca958f","parent":null,"name":"Женщине","ancestors1":[],"path":["Женщине"]},{"_id":"58784774786d2c0d72ca9590","parent":"58784766786d2c0d72ca958f","name":"Одежда","ancestors1":[{"_id":"58784766786d2c0d72ca958f","name":"Женщине"}],"path":["Женщине","Одежда"]},{"_id":"58784791786d2c0d72ca9592","parent":"58784774786d2c0d72ca9590","name":"Куртки","ancestors1":[{"_id":"58784766786d2c0d72ca958f","name":"Женщине"},{"_id":"58784774786d2c0d72ca9590","name":"Одежда"}],"path":["Женщине","Одежда","Куртки"]},{"_id":"58784786786d2c0d72ca9591","parent":"58784774786d2c0d72ca9590","name":"Платья","ancestors1":[{"_id":"58784766786d2c0d72ca958f","name":"Женщине"},{"_id":"58784774786d2c0d72ca9590","name":"Одежда"}],"path":["Женщине","Одежда","Платья"]},{"_id":"5878479a786d2c0d72ca9593","parent":null,"name":"Мужчине","ancestors1":[],"path":["Мужчине"]},{"_id":"587847b5786d2c0d72ca9595","parent":"5878479a786d2c0d72ca9593","name":"Аксессуары","ancestors1":[{"_id":"5878479a786d2c0d72ca9593","name":"Мужчине"}],"path":["Мужчине","Аксессуары"]},{"_id":"587847db786d2c0d72ca9598","parent":"587847b5786d2c0d72ca9595","name":"Кольца","ancestors1":[{"_id":"5878479a786d2c0d72ca9593","name":"Мужчине"},{"_id":"587847b5786d2c0d72ca9595","name":"Аксессуары"}],"path":["Мужчине","Аксессуары","Кольца"]},{"_id":"587847e9786d2c0d72ca9599","parent":"587847b5786d2c0d72ca9595","name":"Цепочки","ancestors1":[{"_id":"5878479a786d2c0d72ca9593","name":"Мужчине"},{"_id":"587847b5786d2c0d72ca9595","name":"Аксессуары"}],"path":["Мужчине","Аксессуары","Цепочки"]},{"_id":"587847a3786d2c0d72ca9594","parent":"5878479a786d2c0d72ca9593","name":"Обувь","ancestors1":[{"_id":"5878479a786d2c0d72ca9593","name":"Мужчине"}],"path":["Мужчине","Обувь"]},{"_id":"587847cd786d2c0d72ca9597","parent":"587847a3786d2c0d72ca9594","name":"Сапоги","ancestors1":[{"_id":"5878479a786d2c0d72ca9593","name":"Мужчине"},{"_id":"587847a3786d2c0d72ca9594","name":"Обувь"}],"path":["Мужчине","Обувь","Сапоги"]},{"_id":"587847bd786d2c0d72ca9596","parent":"587847a3786d2c0d72ca9594","name":"Туфли","ancestors1":[{"_id":"5878479a786d2c0d72ca9593","name":"Мужчине"},{"_id":"587847a3786d2c0d72ca9594","name":"Обувь"}],"path":["Мужчине","Обувь","Туфли"]}]